<?xml version="1.0" encoding="utf-8"?>
<I c="AdventureMoment" i="snippet" m="snippets" n="career_ParkWorker_ChanceCard_14" s="453087">
  <U n="value">
    <L n="_finish_actions">
      <U>
        <L n="action_results">
          <U>
            <L n="loot_actions">
              <T>453142<!--LootActions: loot_Career_ParkWorker_ChanceCard_14A_Fail--></T>
            </L>
            <V n="notification" t="enabled">
              <V n="enabled" t="reference">
                <T n="reference">453203<!--Notification: notification_ChanceCard_ParkWorker_14A_Failure--></T>
              </V>
            </V>
          </U>
          <U>
            <L n="loot_actions">
              <T>453143<!--LootActions: loot_Career_ParkWorker_ChanceCard_14A_Success--></T>
            </L>
            <V n="notification" t="enabled">
              <V n="enabled" t="reference">
                <T n="reference">453204<!--Notification: notification_ChanceCard_ParkWorker_14A_Success--></T>
              </V>
            </V>
            <L n="weight_modifiers">
              <U>
                <T n="weight_multiplier">3</T>
              </U>
            </L>
          </U>
        </L>
        <V n="display_text" t="single">
          <T n="single">0x4005B5C4<!--String: "Give Up and Return Home"--></T>
        </V>
      </U>
      <U>
        <L n="action_results">
          <U>
            <L n="loot_actions">
              <T>453144<!--LootActions: loot_Career_ParkWorker_ChanceCard_14B_Fail--></T>
            </L>
            <V n="notification" t="enabled">
              <V n="enabled" t="reference">
                <T n="reference">453205<!--Notification: notification_ChanceCard_ParkWorker_14B_Failure--></T>
              </V>
            </V>
          </U>
          <U>
            <L n="loot_actions">
              <T>453145<!--LootActions: loot_Career_ParkWorker_ChanceCard_14B_Success--></T>
            </L>
            <V n="notification" t="enabled">
              <V n="enabled" t="reference">
                <T n="reference">453206<!--Notification: notification_ChanceCard_ParkWorker_14B_Success--></T>
              </V>
            </V>
            <L n="weight_modifiers">
              <U>
                <V n="test" t="ranked_statistic">
                  <U n="ranked_statistic">
                    <T n="ranked_stat">460794<!--RankedStatistic: rankedStatistic_ParkWorker_ParkLore--></T>
                    <V n="threshold" t="value_threshold">
                      <U n="value_threshold">
                        <T n="value">4</T>
                      </U>
                    </V>
                  </U>
                </V>
                <T n="weight_multiplier">4</T>
              </U>
              <U>
                <V n="test" t="ranked_statistic">
                  <U n="ranked_statistic">
                    <T n="ranked_stat">460794<!--RankedStatistic: rankedStatistic_ParkWorker_ParkLore--></T>
                    <V n="threshold" t="value_threshold">
                      <U n="value_threshold">
                        <E n="comparison">EQUAL</E>
                        <T n="value">3</T>
                      </U>
                    </V>
                  </U>
                </V>
                <T n="weight_multiplier">3</T>
              </U>
              <U>
                <V n="test" t="ranked_statistic">
                  <U n="ranked_statistic">
                    <T n="ranked_stat">460794<!--RankedStatistic: rankedStatistic_ParkWorker_ParkLore--></T>
                    <V n="threshold" t="value_threshold">
                      <U n="value_threshold">
                        <E n="comparison">EQUAL</E>
                        <T n="value">2</T>
                      </U>
                    </V>
                  </U>
                </V>
                <T n="weight_multiplier">2</T>
              </U>
              <U>
                <V n="test" t="trait">
                  <U n="trait">
                    <L n="whitelist_traits">
                      <T>27914<!--Trait: trait_LovesOutdoors--></T>
                    </L>
                  </U>
                </V>
                <T n="weight_multiplier">1.5</T>
              </U>
            </L>
          </U>
        </L>
        <V n="display_text" t="single">
          <T n="single">0x10D234B2<!--String: "Search Nearby Area"--></T>
        </V>
      </U>
      <U>
        <L n="action_results">
          <U>
            <L n="loot_actions">
              <T>457381<!--LootActions: loot_Career_ParkWorker_ChanceCard_14C_Fail--></T>
            </L>
            <V n="notification" t="enabled">
              <V n="enabled" t="reference">
                <T n="reference">457391<!--Notification: notification_ChanceCard_ParkWorker_14C_Failure--></T>
              </V>
            </V>
          </U>
          <U>
            <L n="loot_actions">
              <T>457382<!--LootActions: loot_Career_ParkWorker_ChanceCard_14C_Success--></T>
            </L>
            <V n="notification" t="enabled">
              <V n="enabled" t="reference">
                <T n="reference">457392<!--Notification: notification_ChanceCard_ParkWorker_14C_Success--></T>
              </V>
            </V>
            <L n="weight_modifiers">
              <U>
                <V n="test" t="ranked_statistic">
                  <U n="ranked_statistic">
                    <T n="ranked_stat">460794<!--RankedStatistic: rankedStatistic_ParkWorker_ParkLore--></T>
                    <V n="threshold" t="value_threshold">
                      <U n="value_threshold">
                        <T n="value">4</T>
                      </U>
                    </V>
                  </U>
                </V>
                <T n="weight_multiplier">4</T>
              </U>
              <U>
                <V n="test" t="ranked_statistic">
                  <U n="ranked_statistic">
                    <T n="ranked_stat">460794<!--RankedStatistic: rankedStatistic_ParkWorker_ParkLore--></T>
                    <V n="threshold" t="value_threshold">
                      <U n="value_threshold">
                        <E n="comparison">EQUAL</E>
                        <T n="value">3</T>
                      </U>
                    </V>
                  </U>
                </V>
                <T n="weight_multiplier">3</T>
              </U>
              <U>
                <V n="test" t="ranked_statistic">
                  <U n="ranked_statistic">
                    <T n="ranked_stat">460794<!--RankedStatistic: rankedStatistic_ParkWorker_ParkLore--></T>
                    <V n="threshold" t="value_threshold">
                      <U n="value_threshold">
                        <E n="comparison">EQUAL</E>
                        <T n="value">2</T>
                      </U>
                    </V>
                  </U>
                </V>
                <T n="weight_multiplier">2</T>
              </U>
              <U>
                <V n="test" t="trait">
                  <U n="trait">
                    <L n="whitelist_traits">
                      <T>27914<!--Trait: trait_LovesOutdoors--></T>
                    </L>
                  </U>
                </V>
                <T n="weight_multiplier">1.5</T>
              </U>
            </L>
          </U>
        </L>
        <V n="display_text" t="single">
          <T n="single">0x42D3E49B<!--String: "Continue Deeper"--></T>
        </V>
      </U>
    </L>
    <V n="_visibility" t="show_dialog">
      <U n="show_dialog">
        <E n="dialog_style">LARGE_ICON</E>
        <V n="icon" t="enabled">
          <V n="enabled" t="resource_key">
            <U n="resource_key">
              <T n="key" p="InEP20\UI\Icons\ChanceCards\EP20_ChanceCards_ParkRangerExpedition2.png">2f7d0004:00000000:65ddd5e683875449</T>
            </U>
          </V>
        </V>
        <V n="text" t="single">
          <T n="single">0xCFBB1CE6<!--String: "While hiking through a quieter part of Miceli Park, {0.SimFirstName} spots a narrow path that doesn't seem to be on any map. No signs, no footprints...just a trail leading deeper into the wild. Some rangers say there are old tools or carvings hidden out here, left behind by the first people who explored the park. It’s hard to tell if those stories are true...but there’s only one way to find out."--></T>
        </V>
        <V n="title" t="enabled">
          <T n="enabled">0x6A2BFCC0<!--String: "Expedition"--></T>
        </V>
      </U>
    </V>
  </U>
</I>