<?xml version="1.0" encoding="utf-8"?>
<I c="Notification" i="snippet" m="snippets" n="notification_ChanceCard_ParkWorker_03A_Failure" s="453159">
  <U n="value">
    <V n="icon" t="disabled" />
    <V n="secondary_icon" t="enabled">
      <V n="enabled" t="participant" />
    </V>
    <V n="text" t="single">
      <T n="single">0x7942C1F8<!--String: "To {0.SimPronounPossessiveDependent} credit, {0.SimFirstName} tried to scare off the bear. When that didn’t work and the bear kept approaching, {0.SimPronounSubjective} resorted to the next step: fetal position. Fortunately, the bear ran right past {0.SimFirstName}, leaving {0.SimPronounObjective} alone, but not before it terrorized the camp, only to be chased off by other camp workers."--></T>
    </V>
    <V n="title" t="disabled" />
  </U>
</I>