<?xml version="1.0" encoding="utf-8"?>
<I c="SituationGoalObjectInteraction" i="situation_goal" m="situations.situation_goal_object_interaction" n="situationGoalObjectInteraction_LiveEvent_EVTSept25_PlayWithCat" s="466636">
  <V n="_display_data" t="enabled">
    <U n="enabled">
      <V n="instance_display_icon" t="enabled">
        <T p="InGame\UI\Icons\Headlines\Final\headline_funnybase.png" n="enabled">2f7d0004:00000000:04bf042e3217bcab</T>
      </V>
      <V n="instance_display_name" t="enabled">
        <T n="enabled">0xEC65A557<!--String: "Play with Your Cat Using a Laser Pointer"--></T>
      </V>
      <V n="instance_display_tooltip" t="enabled">
        <T n="enabled">0xF2B56079<!--String: "It's fun to watch cats play! They chase everything including lasers, their eyes get wide, and their tails wiggle.\n\nSelect a cat and choose to Play with Laser Pointer.\n\nThis optional goal requires <i>Cats & Dogs Expansion Pack</i> to complete."--></T>
      </V>
    </U>
  </V>
  <L n="_goal_loot_list">
    <T>447711<!--SituationGoalLootActions: liveEvent_GoalLoot_CompleteQuestGoal--></T>
  </L>
  <U n="_goal_test">
    <L n="affordances">
      <T>158103<!--SocialSuperInteraction: petSocial_SimToPet_Cat_LaserPointer_Tease_SI--></T>
    </L>
    <E n="test_event">InteractionComplete</E>
  </U>
  <L n="_post_tests">
    <V t="sim_info">
      <U n="sim_info">
        <V n="npc" t="enabled" />
      </U>
    </V>
  </L>
  <T p="InGame\Audio\Bumper\bumper_event_goal_complete.propx" n="audio_sting_on_complete">39b2aa4a:00000000:ed52c39bcc2a7111</T>
  <T n="mandatory">False</T>
  <V n="mtx_bundle" t="enabled">
    <T n="enabled">160075<!--ObjectStateValue: bowlingLane_Values_Results_Sweeper_Left_Child_6_Pins_HL1369--></T>
  </V>
  <V n="tutorial_tip_group" t="enabled">
    <T n="enabled">468817<!--TutorialTipGroup: tutorialTipGroup_LiveEvent_EVTSept25_PlayWithCat--></T>
  </V>
</I>