<?xml version="1.0" encoding="utf-8"?>
<I c="LootActions" i="action" m="interactions.utils.loot" n="loot_Cryptid_ShareFeelings" s="452324">
  <L n="loot_actions">
    <V t="buff">
      <U n="buff">
        <U n="buff">
          <V n="buff_reason" t="enabled">
            <T n="enabled">0x2322A2E1<!--String: "(From Sharing Feelings with Peculiar Plumbird)"--></T>
          </V>
          <T n="buff_type">447402<!--Buff: buff_Cryptid_FeelingsShared--></T>
        </U>
      </U>
    </V>
    <V t="notification_and_dialog">
      <U n="notification_and_dialog">
        <V n="dialog" t="notification">
          <U n="notification">
            <L n="dialog_options">
              <E>DISABLE_CLOSE_BUTTON</E>
            </L>
            <V n="icon" t="enabled">
              <V n="enabled" t="participant">
                <U n="participant">
                  <L n="participant_type">
                    <E>TargetSim</E>
                  </L>
                </U>
              </V>
            </V>
            <V n="secondary_icon" t="enabled">
              <V n="enabled" t="participant">
                <U n="participant">
                  <L n="participant_type">
                    <E>Actor</E>
                  </L>
                </U>
              </V>
            </V>
            <V n="text" t="single">
              <T n="single">0x9DE7F4A8<!--String: "Angry feelings can feel scary, but they're still as natural as you or me. The key is just working to resolve anger over a situation or a Sim by talking it through and thinking about how you can move into a better space. It's important to share these feelings with care. I hope you feel better soon."--></T>
            </V>
            <V n="title" t="enabled">
              <T n="enabled">0x4BAB1B16<!--String: "Feelings Forum!"--></T>
            </V>
            <E n="visual_type">SPEECH</E>
          </U>
        </V>
        <L n="tests">
          <L>
            <V t="mood">
              <U n="mood">
                <T n="mood">14632<!--Mood: Mood_Angry--></T>
              </U>
            </V>
          </L>
        </L>
      </U>
    </V>
    <V t="notification_and_dialog">
      <U n="notification_and_dialog">
        <V n="dialog" t="notification">
          <U n="notification">
            <L n="dialog_options">
              <E>DISABLE_CLOSE_BUTTON</E>
            </L>
            <V n="icon" t="enabled">
              <V n="enabled" t="participant">
                <U n="participant">
                  <L n="participant_type">
                    <E>TargetSim</E>
                  </L>
                </U>
              </V>
            </V>
            <V n="secondary_icon" t="enabled">
              <V n="enabled" t="participant">
                <U n="participant">
                  <L n="participant_type">
                    <E>Actor</E>
                  </L>
                </U>
              </V>
            </V>
            <V n="text" t="single">
              <T n="single">0x8184DE41<!--String: "Feeling bored is the pits, isn't it? When I'm bored, I like to pick up an activity that is comforting to me or check in with another Sim to see if we can chat or do something together, but sometimes I'll stop and see if I've taken a moment to observe what's around me. Y'know, look at things with fresh eyes! "--></T>
            </V>
            <V n="title" t="enabled">
              <T n="enabled">0x4BAB1B16<!--String: "Feelings Forum!"--></T>
            </V>
            <E n="visual_type">SPEECH</E>
          </U>
        </V>
        <L n="tests">
          <L>
            <V t="mood">
              <U n="mood">
                <T n="mood">14633<!--Mood: Mood_Bored--></T>
              </U>
            </V>
          </L>
        </L>
      </U>
    </V>
    <V t="notification_and_dialog">
      <U n="notification_and_dialog">
        <V n="dialog" t="notification">
          <U n="notification">
            <L n="dialog_options">
              <E>DISABLE_CLOSE_BUTTON</E>
            </L>
            <V n="icon" t="enabled">
              <V n="enabled" t="participant">
                <U n="participant">
                  <L n="participant_type">
                    <E>TargetSim</E>
                  </L>
                </U>
              </V>
            </V>
            <V n="secondary_icon" t="enabled">
              <V n="enabled" t="participant">
                <U n="participant">
                  <L n="participant_type">
                    <E>Actor</E>
                  </L>
                </U>
              </V>
            </V>
            <V n="text" t="single">
              <T n="single">0xE863EE5F<!--String: "Look at you—cool, calm, collected and...confident! I'm proud of you for being proud of yourself. Best thing you can do when you're like this is ride those airstreams and soar as high as you can, my friend. Thanks for being you!"--></T>
            </V>
            <V n="title" t="enabled">
              <T n="enabled">0x4BAB1B16<!--String: "Feelings Forum!"--></T>
            </V>
            <E n="visual_type">SPEECH</E>
          </U>
        </V>
        <L n="tests">
          <L>
            <V t="mood">
              <U n="mood">
                <T n="mood">14634<!--Mood: Mood_Confident--></T>
              </U>
            </V>
          </L>
        </L>
      </U>
    </V>
    <V t="notification_and_dialog">
      <U n="notification_and_dialog">
        <V n="dialog" t="notification">
          <U n="notification">
            <L n="dialog_options">
              <E>DISABLE_CLOSE_BUTTON</E>
            </L>
            <V n="icon" t="enabled">
              <V n="enabled" t="participant">
                <U n="participant">
                  <L n="participant_type">
                    <E>TargetSim</E>
                  </L>
                </U>
              </V>
            </V>
            <V n="secondary_icon" t="enabled">
              <V n="enabled" t="participant">
                <U n="participant">
                  <L n="participant_type">
                    <E>Actor</E>
                  </L>
                </U>
              </V>
            </V>
            <V n="text" t="single">
              <T n="single">0x6539444<!--String: "Oh, pinfeathers. Embarrassing things happen to every Sim. One day I had something funny stuck to my beak all day and no one even told me about it. I felt silly—but if dwell on that too long, I'll never feel better. Push through those tough emotions, friend!"--></T>
            </V>
            <V n="title" t="enabled">
              <T n="enabled">0x4BAB1B16<!--String: "Feelings Forum!"--></T>
            </V>
            <E n="visual_type">SPEECH</E>
          </U>
        </V>
        <L n="tests">
          <L>
            <V t="mood">
              <U n="mood">
                <T n="mood">14635<!--Mood: Mood_Embarrassed--></T>
              </U>
            </V>
          </L>
        </L>
      </U>
    </V>
    <V t="notification_and_dialog">
      <U n="notification_and_dialog">
        <V n="dialog" t="notification">
          <U n="notification">
            <L n="dialog_options">
              <E>DISABLE_CLOSE_BUTTON</E>
            </L>
            <V n="icon" t="enabled">
              <V n="enabled" t="participant">
                <U n="participant">
                  <L n="participant_type">
                    <E>TargetSim</E>
                  </L>
                </U>
              </V>
            </V>
            <V n="secondary_icon" t="enabled">
              <V n="enabled" t="participant">
                <U n="participant">
                  <L n="participant_type">
                    <E>Actor</E>
                  </L>
                </U>
              </V>
            </V>
            <V n="text" t="single">
              <T n="single">0x7D179356<!--String: "Oh, you're feeling energized right now? I love that for you—get out there and conquer the world, my fine featherless friend."--></T>
            </V>
            <V n="title" t="enabled">
              <T n="enabled">0x4BAB1B16<!--String: "Feelings Forum!"--></T>
            </V>
            <E n="visual_type">SPEECH</E>
          </U>
        </V>
        <L n="tests">
          <L>
            <V t="mood">
              <U n="mood">
                <T n="mood">14636<!--Mood: Mood_Energized--></T>
              </U>
            </V>
          </L>
        </L>
      </U>
    </V>
    <V t="notification_and_dialog">
      <U n="notification_and_dialog">
        <V n="dialog" t="notification">
          <U n="notification">
            <L n="dialog_options">
              <E>DISABLE_CLOSE_BUTTON</E>
            </L>
            <V n="icon" t="enabled">
              <V n="enabled" t="participant">
                <U n="participant">
                  <L n="participant_type">
                    <E>TargetSim</E>
                  </L>
                </U>
              </V>
            </V>
            <V n="secondary_icon" t="enabled">
              <V n="enabled" t="participant">
                <U n="participant">
                  <L n="participant_type">
                    <E>Actor</E>
                  </L>
                </U>
              </V>
            </V>
            <V n="text" t="single">
              <T n="single">0x8E8DB6FF<!--String: "Feeling fine, eh? Stable as a table? That's what we like to hear—some Sims think that's just neutral and a little less interesting, but feeling fine means you can be a calm and inquisitive Sim just checkin' out the scene, right?"--></T>
            </V>
            <V n="title" t="enabled">
              <T n="enabled">0x4BAB1B16<!--String: "Feelings Forum!"--></T>
            </V>
            <E n="visual_type">SPEECH</E>
          </U>
        </V>
        <L n="tests">
          <L>
            <V t="mood">
              <U n="mood">
                <T n="mood">14637<!--Mood: Mood_Fine--></T>
              </U>
            </V>
          </L>
        </L>
      </U>
    </V>
    <V t="notification_and_dialog">
      <U n="notification_and_dialog">
        <V n="dialog" t="notification">
          <U n="notification">
            <L n="dialog_options">
              <E>DISABLE_CLOSE_BUTTON</E>
            </L>
            <V n="icon" t="enabled">
              <V n="enabled" t="participant">
                <U n="participant">
                  <L n="participant_type">
                    <E>TargetSim</E>
                  </L>
                </U>
              </V>
            </V>
            <V n="secondary_icon" t="enabled">
              <V n="enabled" t="participant">
                <U n="participant">
                  <L n="participant_type">
                    <E>Actor</E>
                  </L>
                </U>
              </V>
            </V>
            <V n="text" t="single">
              <T n="single">0x9EE7C270<!--String: "Oh, goodness. You're making me blush! I'm glad you shared, but...well, share appropriately!"--></T>
            </V>
            <V n="title" t="enabled">
              <T n="enabled">0x4BAB1B16<!--String: "Feelings Forum!"--></T>
            </V>
            <E n="visual_type">SPEECH</E>
          </U>
        </V>
        <L n="tests">
          <L>
            <V t="mood">
              <U n="mood">
                <T n="mood">14638<!--Mood: Mood_Flirty--></T>
              </U>
            </V>
          </L>
        </L>
      </U>
    </V>
    <V t="notification_and_dialog">
      <U n="notification_and_dialog">
        <V n="dialog" t="notification">
          <U n="notification">
            <L n="dialog_options">
              <E>DISABLE_CLOSE_BUTTON</E>
            </L>
            <V n="icon" t="enabled">
              <V n="enabled" t="participant">
                <U n="participant">
                  <L n="participant_type">
                    <E>TargetSim</E>
                  </L>
                </U>
              </V>
            </V>
            <V n="secondary_icon" t="enabled">
              <V n="enabled" t="participant">
                <U n="participant">
                  <L n="participant_type">
                    <E>Actor</E>
                  </L>
                </U>
              </V>
            </V>
            <V n="text" t="single">
              <T n="single">0xE92961A4<!--String: "You definitely have the most focused, determined face I've seen on a Sim in a while. Go do something with that energy—work on a Skill, maybe? You can do it!"--></T>
            </V>
            <V n="title" t="enabled">
              <T n="enabled">0x4BAB1B16<!--String: "Feelings Forum!"--></T>
            </V>
            <E n="visual_type">SPEECH</E>
          </U>
        </V>
        <L n="tests">
          <L>
            <V t="mood">
              <U n="mood">
                <T n="mood">14639<!--Mood: Mood_Focused--></T>
              </U>
            </V>
          </L>
        </L>
      </U>
    </V>
    <V t="notification_and_dialog">
      <U n="notification_and_dialog">
        <V n="dialog" t="notification">
          <U n="notification">
            <L n="dialog_options">
              <E>DISABLE_CLOSE_BUTTON</E>
            </L>
            <V n="icon" t="enabled">
              <V n="enabled" t="participant">
                <U n="participant">
                  <L n="participant_type">
                    <E>TargetSim</E>
                  </L>
                </U>
              </V>
            </V>
            <V n="secondary_icon" t="enabled">
              <V n="enabled" t="participant">
                <U n="participant">
                  <L n="participant_type">
                    <E>Actor</E>
                  </L>
                </U>
              </V>
            </V>
            <V n="text" t="single">
              <T n="single">0xF3946E52<!--String: "Being happy is the BEST, isn't it! I love feeling like everything is going well and that I have all that I need. The best thing to do when you're happy? Sharing your happiness with others!"--></T>
            </V>
            <V n="title" t="enabled">
              <T n="enabled">0x4BAB1B16<!--String: "Feelings Forum!"--></T>
            </V>
            <E n="visual_type">SPEECH</E>
          </U>
        </V>
        <L n="tests">
          <L>
            <V t="mood">
              <U n="mood">
                <T n="mood">14640<!--Mood: Mood_Happy--></T>
              </U>
            </V>
          </L>
        </L>
      </U>
    </V>
    <V t="notification_and_dialog">
      <U n="notification_and_dialog">
        <V n="dialog" t="notification">
          <U n="notification">
            <L n="dialog_options">
              <E>DISABLE_CLOSE_BUTTON</E>
            </L>
            <V n="icon" t="enabled">
              <V n="enabled" t="participant">
                <U n="participant">
                  <L n="participant_type">
                    <E>TargetSim</E>
                  </L>
                </U>
              </V>
            </V>
            <V n="secondary_icon" t="enabled">
              <V n="enabled" t="participant">
                <U n="participant">
                  <L n="participant_type">
                    <E>Actor</E>
                  </L>
                </U>
              </V>
            </V>
            <V n="text" t="single">
              <T n="single">0x18109223<!--String: "Y'know, when I'm inspired I love to create. It's a bit hard to do papercraft with wings, but that might be fun for you. Or maybe you can paint or play piano? Take advantage of this great mood, friend!"--></T>
            </V>
            <V n="title" t="enabled">
              <T n="enabled">0x4BAB1B16<!--String: "Feelings Forum!"--></T>
            </V>
            <E n="visual_type">SPEECH</E>
          </U>
        </V>
        <L n="tests">
          <L>
            <V t="mood">
              <U n="mood">
                <T n="mood">14641<!--Mood: Mood_Inspired--></T>
              </U>
            </V>
          </L>
        </L>
      </U>
    </V>
    <V t="notification_and_dialog">
      <U n="notification_and_dialog">
        <V n="dialog" t="notification">
          <U n="notification">
            <L n="dialog_options">
              <E>DISABLE_CLOSE_BUTTON</E>
            </L>
            <V n="icon" t="enabled">
              <V n="enabled" t="participant">
                <U n="participant">
                  <L n="participant_type">
                    <E>TargetSim</E>
                  </L>
                </U>
              </V>
            </V>
            <V n="secondary_icon" t="enabled">
              <V n="enabled" t="participant">
                <U n="participant">
                  <L n="participant_type">
                    <E>Actor</E>
                  </L>
                </U>
              </V>
            </V>
            <V n="text" t="single">
              <T n="single">0x89E85D40<!--String: "Playful is the BEST emotion! Sorry, I'm biased. I just love having fun and being a little bit silly. "--></T>
            </V>
            <V n="title" t="enabled">
              <T n="enabled">0x4BAB1B16<!--String: "Feelings Forum!"--></T>
            </V>
            <E n="visual_type">SPEECH</E>
          </U>
        </V>
        <L n="tests">
          <L>
            <V t="mood">
              <U n="mood">
                <T n="mood">14642<!--Mood: Mood_Playful--></T>
              </U>
            </V>
          </L>
        </L>
      </U>
    </V>
    <V t="notification_and_dialog">
      <U n="notification_and_dialog">
        <V n="dialog" t="notification">
          <U n="notification">
            <L n="dialog_options">
              <E>DISABLE_CLOSE_BUTTON</E>
            </L>
            <V n="icon" t="enabled">
              <V n="enabled" t="participant">
                <U n="participant">
                  <L n="participant_type">
                    <E>TargetSim</E>
                  </L>
                </U>
              </V>
            </V>
            <V n="secondary_icon" t="enabled">
              <V n="enabled" t="participant">
                <U n="participant">
                  <L n="participant_type">
                    <E>Actor</E>
                  </L>
                </U>
              </V>
            </V>
            <V n="text" t="single">
              <T n="single">0x25EABF39<!--String: "Being sad is really tough. Sometimes it goes away fast, but sometimes it can linger. The important thing to remember is that you have Sims to reach out to when things are tough and that you're allowed to feel sad feelings. Just remember: you aren't alone. I'm always here for ya!"--></T>
            </V>
            <V n="title" t="enabled">
              <T n="enabled">0x4BAB1B16<!--String: "Feelings Forum!"--></T>
            </V>
            <E n="visual_type">SPEECH</E>
          </U>
        </V>
        <L n="tests">
          <L>
            <V t="mood">
              <U n="mood">
                <T n="mood">14643<!--Mood: Mood_Sad--></T>
              </U>
            </V>
          </L>
        </L>
      </U>
    </V>
    <V t="notification_and_dialog">
      <U n="notification_and_dialog">
        <V n="dialog" t="notification">
          <U n="notification">
            <L n="dialog_options">
              <E>DISABLE_CLOSE_BUTTON</E>
            </L>
            <V n="icon" t="enabled">
              <V n="enabled" t="participant">
                <U n="participant">
                  <L n="participant_type">
                    <E>TargetSim</E>
                  </L>
                </U>
              </V>
            </V>
            <V n="secondary_icon" t="enabled">
              <V n="enabled" t="participant">
                <U n="participant">
                  <L n="participant_type">
                    <E>Actor</E>
                  </L>
                </U>
              </V>
            </V>
            <V n="text" t="single">
              <T n="single">0x1D60BBE6<!--String: "You know what I'm afraid of? Swimming. What's in that water, huh? What's down there! Nothing I wanna see, that's for sure. Obviously, you can work to conquer your fears and that's great...but sometimes you just gotta ground yourself. When I get freaked out about swimming, I identify things I can see, touch, hear, smell, and taste with my lil beak. Maybe that'll help, right?"--></T>
            </V>
            <V n="title" t="enabled">
              <T n="enabled">0x4BAB1B16<!--String: "Feelings Forum!"--></T>
            </V>
            <E n="visual_type">SPEECH</E>
          </U>
        </V>
        <L n="tests">
          <L>
            <V t="mood">
              <U n="mood">
                <T n="mood">251719<!--Mood: Mood_Scared--></T>
              </U>
            </V>
          </L>
        </L>
      </U>
    </V>
    <V t="notification_and_dialog">
      <U n="notification_and_dialog">
        <V n="dialog" t="notification">
          <U n="notification">
            <L n="dialog_options">
              <E>DISABLE_CLOSE_BUTTON</E>
            </L>
            <V n="icon" t="enabled">
              <V n="enabled" t="participant">
                <U n="participant">
                  <L n="participant_type">
                    <E>TargetSim</E>
                  </L>
                </U>
              </V>
            </V>
            <V n="secondary_icon" t="enabled">
              <V n="enabled" t="participant">
                <U n="participant">
                  <L n="participant_type">
                    <E>Actor</E>
                  </L>
                </U>
              </V>
            </V>
            <V n="text" t="single">
              <T n="single">0x5BFF8D7A<!--String: "Uh-oh. Your feathers seem ruffled for sure. Maybe taking a breather or getting some rest would help you!"--></T>
            </V>
            <V n="title" t="enabled">
              <T n="enabled">0x4BAB1B16<!--String: "Feelings Forum!"--></T>
            </V>
            <E n="visual_type">SPEECH</E>
          </U>
        </V>
        <L n="tests">
          <L>
            <V t="mood">
              <U n="mood">
                <T n="mood">14645<!--Mood: Mood_Stressed--></T>
              </U>
            </V>
          </L>
          <L>
            <V t="mood">
              <U n="mood">
                <T n="mood">14646<!--Mood: Mood_Uncomfortable--></T>
              </U>
            </V>
          </L>
          <L>
            <V t="mood">
              <U n="mood">
                <T n="mood">201531<!--Mood: Mood_Possessed--></T>
              </U>
            </V>
          </L>
          <L>
            <V t="mood">
              <U n="mood">
                <T n="mood">14644<!--Mood: Mood_Dazed--></T>
              </U>
            </V>
          </L>
        </L>
      </U>
    </V>
  </L>
</I>