<?xml version="1.0" encoding="utf-8"?>
<I c="Buff" i="buff" m="buffs.buff" n="buff_EP20_Asp_ButterflyAngry" s="454892">
  <V n="_temporary_commodity_info" t="enabled">
    <U n="enabled">
      <L n="categories">
        <E>Angry_Buffs</E>
      </L>
      <T n="max_duration">120</T>
    </U>
  </V>
  <T p="InGame\Audio\Stings\sting_buff_gain.propx" n="audio_sting_on_add">39b2aa4a:00000000:8af8b916cf64c646</T>
  <T p="InGame\Audio\Stings\sting_buff_loss.propx" n="audio_sting_on_remove">39b2aa4a:00000000:3bf33216a25546ea</T>
  <T n="buff_description">0x6DA5EB10<!--String: "<i>What did this butterfly just say?!</i> {0.SimFirstName} has had enough of this rude little winged buffoon!"--></T>
  <T n="buff_name">0x883B4C3F<!--String: "Excuse Me?!"--></T>
  <T n="icon" p="InEP20\UI\Icons\Buffs\buffs_ExcuseMEButterfly_neg.png">2f7d0004:00000000:4702540ead4f156d</T>
  <T n="mood_type">14632<!--Mood: Mood_Angry--></T>
  <T n="mood_weight">2</T>
</I>