<?xml version="1.0" encoding="utf-8"?>
<I c="Objective" i="objective" m="event_testing.objective_tuning" n="objective_ChildhoodInspiration_FuturePolitician_3" s="473228">
  <T n="display_text">0xB30D5F30<!--String: ""The more people I know, the more votes I get!""--></T>
  <V n="objective_completion_type" t="iterations">
    <U n="iterations">
      <T n="iterations_required_to_pass">2</T>
    </U>
  </V>
  <V n="objective_test" t="relationship_bit">
    <U n="relationship_bit">
      <L n="relationship_bits">
        <T>15792<!--RelationshipBit: friendship-acquaintances--></T>
      </L>
    </U>
  </V>
  <T n="tooltip">0x9F34B36D<!--String: "\n<b><font color='#2182E6'>Make {1.Number} Acquaintances.</font></b>\n\nIf I want to be a great leader someday, I'll need to meet lots of Sims and get to know what matters to them."--></T>
</I>