<?xml version="1.0" encoding="utf-8"?>
<I c="RandomWeightedLoot" i="action" m="interactions.utils.loot" n="randomWeightedLoot_UnfinishedBusiness_AddGoal_Success" s="381279">
  <L n="random_loot_actions">
    <U>
      <V n="action" t="unfinished_business_loot">
        <U n="unfinished_business_loot">
          <V n="operation" t="add_objective">
            <U n="add_objective">
              <T n="objective">382477<!--Objective: Objectives_UnfinishedBusiness_Success_GreatParent--></T>
            </U>
          </V>
          <L n="tests">
            <L>
              <V t="objective_available_test">
                <U n="objective_available_test">
                  <T n="objective">382477<!--Objective: Objectives_UnfinishedBusiness_Success_GreatParent--></T>
                </U>
              </V>
            </L>
          </L>
        </U>
      </V>
      <U n="weight">
        <T n="base_value">3</T>
      </U>
    </U>
    <U>
      <V n="action" t="unfinished_business_loot">
        <U n="unfinished_business_loot">
          <V n="operation" t="add_objective">
            <U n="add_objective">
              <T n="objective">382468<!--Objective: Objectives_UnfinishedBusiness_Success_AttendMovieAwards--></T>
            </U>
          </V>
          <L n="tests">
            <L>
              <V t="objective_available_test">
                <U n="objective_available_test">
                  <T n="objective">382468<!--Objective: Objectives_UnfinishedBusiness_Success_AttendMovieAwards--></T>
                </U>
              </V>
            </L>
          </L>
        </U>
      </V>
    </U>
    <U>
      <V n="action" t="unfinished_business_loot">
        <U n="unfinished_business_loot">
          <V n="operation" t="add_objective">
            <U n="add_objective">
              <T n="objective">382467<!--Objective: Objectives_UnfinishedBusiness_Success_BecomeRecognized--></T>
            </U>
          </V>
          <L n="tests">
            <L>
              <V t="objective_available_test">
                <U n="objective_available_test">
                  <T n="objective">382467<!--Objective: Objectives_UnfinishedBusiness_Success_BecomeRecognized--></T>
                </U>
              </V>
            </L>
          </L>
        </U>
      </V>
    </U>
    <U>
      <V n="action" t="unfinished_business_loot">
        <U n="unfinished_business_loot">
          <V n="operation" t="add_objective">
            <U n="add_objective">
              <T n="objective">382469<!--Objective: Objectives_UnfinishedBusiness_Success_FinishUniversity--></T>
            </U>
          </V>
          <L n="tests">
            <L>
              <V t="objective_available_test">
                <U n="objective_available_test">
                  <T n="objective">382469<!--Objective: Objectives_UnfinishedBusiness_Success_FinishUniversity--></T>
                </U>
              </V>
            </L>
          </L>
        </U>
      </V>
    </U>
    <U>
      <V n="action" t="unfinished_business_loot">
        <U n="unfinished_business_loot">
          <V n="operation" t="add_objective">
            <U n="add_objective">
              <T n="objective">382482<!--Objective: Objectives_UnfinishedBusiness_Success_WinDebate--></T>
            </U>
          </V>
          <L n="tests">
            <L>
              <V t="objective_available_test">
                <U n="objective_available_test">
                  <T n="objective">382482<!--Objective: Objectives_UnfinishedBusiness_Success_WinDebate--></T>
                </U>
              </V>
            </L>
          </L>
        </U>
      </V>
    </U>
    <U>
      <V n="action" t="unfinished_business_loot">
        <U n="unfinished_business_loot">
          <V n="operation" t="add_objective">
            <U n="add_objective">
              <T n="objective">382470<!--Objective: Objectives_UnfinishedBusiness_Success_HorseCompetition--></T>
            </U>
          </V>
          <L n="tests">
            <L>
              <V t="objective_available_test">
                <U n="objective_available_test">
                  <T n="objective">382470<!--Objective: Objectives_UnfinishedBusiness_Success_HorseCompetition--></T>
                </U>
              </V>
            </L>
          </L>
        </U>
      </V>
      <U n="weight">
        <L n="multipliers">
          <U>
            <T n="multiplier">6</T>
            <L n="tests">
              <L>
                <V t="trait">
                  <U n="trait">
                    <L n="whitelist_traits">
                      <T>320965<!--Trait: trait_HorseLover--></T>
                      <T>320988<!--Trait: trait_Rancher--></T>
                    </L>
                  </U>
                </V>
              </L>
            </L>
          </U>
        </L>
      </U>
    </U>
    <U>
      <V n="action" t="unfinished_business_loot">
        <U n="unfinished_business_loot">
          <V n="operation" t="add_objective">
            <U n="add_objective">
              <T n="objective">382478<!--Objective: objectives_UnfinishedBusiness_Success_BigFish--></T>
            </U>
          </V>
          <L n="tests">
            <L>
              <V t="objective_available_test">
                <U n="objective_available_test">
                  <T n="objective">382478<!--Objective: objectives_UnfinishedBusiness_Success_BigFish--></T>
                </U>
              </V>
            </L>
          </L>
        </U>
      </V>
      <U n="weight">
        <L n="multipliers">
          <U>
            <T n="multiplier">4</T>
            <L n="tests">
              <L>
                <V t="trait">
                  <U n="trait">
                    <L n="whitelist_traits">
                      <T>27914<!--Trait: trait_LovesOutdoors--></T>
                      <T>248831<!--Trait: trait_Lifestyles_Outdoorsy--></T>
                    </L>
                  </U>
                </V>
              </L>
            </L>
          </U>
        </L>
      </U>
    </U>
    <U>
      <V n="action" t="unfinished_business_loot">
        <U n="unfinished_business_loot">
          <V n="operation" t="add_objective">
            <U n="add_objective">
              <T n="objective">382483<!--Objective: objectives_UnfinishedBusiness_Success_Charity--></T>
            </U>
          </V>
          <L n="tests">
            <L>
              <V t="objective_available_test">
                <U n="objective_available_test">
                  <T n="objective">382483<!--Objective: objectives_UnfinishedBusiness_Success_Charity--></T>
                </U>
              </V>
            </L>
          </L>
        </U>
      </V>
      <U n="weight">
        <L n="multipliers">
          <U>
            <T n="multiplier">6</T>
            <L n="tests">
              <L>
                <V t="trait">
                  <U n="trait">
                    <L n="whitelist_traits">
                      <T>341152<!--Trait: trait_Generous--></T>
                      <T>27915<!--Trait: trait_Good--></T>
                    </L>
                  </U>
                </V>
              </L>
            </L>
          </U>
        </L>
      </U>
    </U>
    <U>
      <V n="action" t="unfinished_business_loot">
        <U n="unfinished_business_loot">
          <V n="operation" t="add_objective">
            <U n="add_objective">
              <T n="objective">382479<!--Objective: objectives_UnfinishedBusiness_Success_CoolMusician--></T>
            </U>
          </V>
          <L n="tests">
            <L>
              <V t="objective_available_test">
                <U n="objective_available_test">
                  <T n="objective">382479<!--Objective: objectives_UnfinishedBusiness_Success_CoolMusician--></T>
                </U>
              </V>
            </L>
          </L>
        </U>
      </V>
      <U n="weight">
        <L n="multipliers">
          <U>
            <T n="multiplier">4</T>
            <L n="tests">
              <L>
                <V t="trait">
                  <U n="trait">
                    <L n="whitelist_traits">
                      <T>9604<!--Trait: trait_MusicLover--></T>
                    </L>
                  </U>
                </V>
              </L>
            </L>
          </U>
        </L>
      </U>
    </U>
    <U>
      <V n="action" t="unfinished_business_loot">
        <U n="unfinished_business_loot">
          <V n="operation" t="add_objective">
            <U n="add_objective">
              <T n="objective">382475<!--Objective: objectives_UnfinishedBusiness_Success_DecorateArt--></T>
            </U>
          </V>
          <L n="tests">
            <L>
              <V t="objective_available_test">
                <U n="objective_available_test">
                  <T n="objective">382475<!--Objective: objectives_UnfinishedBusiness_Success_DecorateArt--></T>
                </U>
              </V>
            </L>
          </L>
        </U>
      </V>
    </U>
    <U>
      <V n="action" t="unfinished_business_loot">
        <U n="unfinished_business_loot">
          <V n="operation" t="add_objective">
            <U n="add_objective">
              <T n="objective">382464<!--Objective: objectives_UnfinishedBusiness_Success_ExpensiveHouse--></T>
            </U>
          </V>
          <L n="tests">
            <L>
              <V t="objective_available_test">
                <U n="objective_available_test">
                  <T n="objective">382464<!--Objective: objectives_UnfinishedBusiness_Success_ExpensiveHouse--></T>
                </U>
              </V>
            </L>
          </L>
        </U>
      </V>
      <U n="weight">
        <L n="multipliers">
          <U>
            <T n="multiplier">6</T>
            <L n="tests">
              <L>
                <V t="trait">
                  <U n="trait">
                    <L n="whitelist_traits">
                      <T>27913<!--Trait: trait_Materialistic--></T>
                    </L>
                  </U>
                </V>
              </L>
            </L>
          </U>
        </L>
      </U>
    </U>
    <U>
      <V n="action" t="unfinished_business_loot">
        <U n="unfinished_business_loot">
          <V n="operation" t="add_objective">
            <U n="add_objective">
              <T n="objective">382471<!--Objective: objectives_UnfinishedBusiness_Success_GetFit--></T>
            </U>
          </V>
          <L n="tests">
            <L>
              <V t="objective_available_test">
                <U n="objective_available_test">
                  <T n="objective">382471<!--Objective: objectives_UnfinishedBusiness_Success_GetFit--></T>
                </U>
              </V>
            </L>
          </L>
        </U>
      </V>
      <U n="weight">
        <L n="multipliers">
          <U>
            <T n="multiplier">6</T>
            <L n="tests">
              <L>
                <V t="trait">
                  <U n="trait">
                    <L n="whitelist_traits">
                      <T>27419<!--Trait: trait_active--></T>
                    </L>
                  </U>
                </V>
              </L>
            </L>
          </U>
        </L>
      </U>
    </U>
    <U>
      <V n="action" t="unfinished_business_loot">
        <U n="unfinished_business_loot">
          <V n="operation" t="add_objective">
            <U n="add_objective">
              <T n="objective">382472<!--Objective: objectives_UnfinishedBusiness_Success_GetSmart--></T>
            </U>
          </V>
          <L n="tests">
            <L>
              <V t="objective_available_test">
                <U n="objective_available_test">
                  <T n="objective">382472<!--Objective: objectives_UnfinishedBusiness_Success_GetSmart--></T>
                </U>
              </V>
            </L>
          </L>
        </U>
      </V>
      <U n="weight">
        <L n="multipliers">
          <U>
            <T n="multiplier">4</T>
            <L n="tests">
              <L>
                <V t="trait">
                  <U n="trait">
                    <L n="whitelist_traits">
                      <T>27917<!--Trait: trait_Genius--></T>
                    </L>
                  </U>
                </V>
              </L>
            </L>
          </U>
        </L>
      </U>
    </U>
    <U>
      <V n="action" t="unfinished_business_loot">
        <U n="unfinished_business_loot">
          <V n="operation" t="add_objective">
            <U n="add_objective">
              <T n="objective">382480<!--Objective: objectives_UnfinishedBusiness_Success_GreatestGamer--></T>
            </U>
          </V>
          <L n="tests">
            <L>
              <V t="objective_available_test">
                <U n="objective_available_test">
                  <T n="objective">382480<!--Objective: objectives_UnfinishedBusiness_Success_GreatestGamer--></T>
                </U>
              </V>
            </L>
          </L>
        </U>
      </V>
      <U n="weight">
        <L n="multipliers">
          <U>
            <T n="multiplier">6</T>
            <L n="tests">
              <L>
                <V t="trait">
                  <U n="trait">
                    <L n="whitelist_traits">
                      <T>16841<!--Trait: trait_Geek--></T>
                      <T>341153<!--Trait: trait_Cringe--></T>
                    </L>
                  </U>
                </V>
              </L>
            </L>
          </U>
        </L>
      </U>
    </U>
    <U>
      <V n="action" t="unfinished_business_loot">
        <U n="unfinished_business_loot">
          <V n="operation" t="add_objective">
            <U n="add_objective">
              <T n="objective">382465<!--Objective: objectives_UnfinishedBusiness_Success_MoneyInBank--></T>
            </U>
          </V>
          <L n="tests">
            <L>
              <V t="objective_available_test">
                <U n="objective_available_test">
                  <T n="objective">382465<!--Objective: objectives_UnfinishedBusiness_Success_MoneyInBank--></T>
                </U>
              </V>
            </L>
          </L>
        </U>
      </V>
    </U>
    <U>
      <V n="action" t="unfinished_business_loot">
        <U n="unfinished_business_loot">
          <V n="operation" t="add_objective">
            <U n="add_objective">
              <T n="objective">382466<!--Objective: objectives_UnfinishedBusiness_Success_MoreMoney--></T>
            </U>
          </V>
          <L n="tests">
            <L>
              <V t="objective_available_test">
                <U n="objective_available_test">
                  <T n="objective">382466<!--Objective: objectives_UnfinishedBusiness_Success_MoreMoney--></T>
                </U>
              </V>
            </L>
          </L>
        </U>
      </V>
    </U>
    <U>
      <V n="action" t="unfinished_business_loot">
        <U n="unfinished_business_loot">
          <V n="operation" t="add_objective">
            <U n="add_objective">
              <T n="objective">382473<!--Objective: objectives_UnfinishedBusiness_Success_QuitJob--></T>
            </U>
          </V>
          <L n="tests">
            <L>
              <V t="objective_available_test">
                <U n="objective_available_test">
                  <T n="objective">382473<!--Objective: objectives_UnfinishedBusiness_Success_QuitJob--></T>
                </U>
              </V>
            </L>
          </L>
        </U>
      </V>
    </U>
    <U>
      <V n="action" t="unfinished_business_loot">
        <U n="unfinished_business_loot">
          <V n="operation" t="add_objective">
            <U n="add_objective">
              <T n="objective">382474<!--Objective: objectives_UnfinishedBusiness_Success_RenovateBackyard--></T>
            </U>
          </V>
          <L n="tests">
            <L>
              <V t="objective_available_test">
                <U n="objective_available_test">
                  <T n="objective">382474<!--Objective: objectives_UnfinishedBusiness_Success_RenovateBackyard--></T>
                </U>
              </V>
            </L>
          </L>
        </U>
      </V>
    </U>
    <U>
      <V n="action" t="unfinished_business_loot">
        <U n="unfinished_business_loot">
          <V n="operation" t="add_objective">
            <U n="add_objective">
              <T n="objective">382476<!--Objective: objectives_UnfinishedBusiness_Success_SuperGhost--></T>
            </U>
          </V>
          <L n="tests">
            <L>
              <V t="objective_available_test">
                <U n="objective_available_test">
                  <T n="objective">382476<!--Objective: objectives_UnfinishedBusiness_Success_SuperGhost--></T>
                </U>
              </V>
            </L>
          </L>
        </U>
      </V>
    </U>
    <U>
      <V n="action" t="unfinished_business_loot">
        <U n="unfinished_business_loot">
          <V n="operation" t="add_objective">
            <U n="add_objective">
              <T n="objective">398413<!--Objective: Objectives_UnfinishedBusiness_Success_Basketball--></T>
            </U>
          </V>
          <L n="tests">
            <L>
              <V t="objective_available_test">
                <U n="objective_available_test">
                  <T n="objective">398413<!--Objective: Objectives_UnfinishedBusiness_Success_Basketball--></T>
                </U>
              </V>
            </L>
          </L>
        </U>
      </V>
    </U>
    <U>
      <V n="action" t="unfinished_business_loot">
        <U n="unfinished_business_loot">
          <V n="operation" t="add_objective">
            <U n="add_objective">
              <T n="objective">398394<!--Objective: Objectives_UnfinishedBusiness_Success_Bowling--></T>
            </U>
          </V>
          <L n="tests">
            <L>
              <V t="objective_available_test">
                <U n="objective_available_test">
                  <T n="objective">398394<!--Objective: Objectives_UnfinishedBusiness_Success_Bowling--></T>
                </U>
              </V>
            </L>
          </L>
        </U>
      </V>
    </U>
    <U>
      <V n="action" t="unfinished_business_loot">
        <U n="unfinished_business_loot">
          <V n="operation" t="add_objective">
            <U n="add_objective">
              <T n="objective">398424<!--Objective: Objectives_UnfinishedBusiness_Success_DJMixing--></T>
            </U>
          </V>
          <L n="tests">
            <L>
              <V t="objective_available_test">
                <U n="objective_available_test">
                  <T n="objective">398424<!--Objective: Objectives_UnfinishedBusiness_Success_DJMixing--></T>
                </U>
              </V>
            </L>
          </L>
        </U>
      </V>
    </U>
    <U>
      <V n="action" t="unfinished_business_loot">
        <U n="unfinished_business_loot">
          <V n="operation" t="add_objective">
            <U n="add_objective">
              <T n="objective">398399<!--Objective: Objectives_UnfinishedBusiness_Success_Serenity--></T>
            </U>
          </V>
          <L n="tests">
            <L>
              <V t="objective_available_test">
                <U n="objective_available_test">
                  <T n="objective">398399<!--Objective: Objectives_UnfinishedBusiness_Success_Serenity--></T>
                </U>
              </V>
            </L>
          </L>
        </U>
      </V>
      <U n="weight">
        <L n="multipliers">
          <U>
            <T n="multiplier">6</T>
            <L n="tests">
              <L>
                <V t="trait">
                  <U n="trait">
                    <L n="whitelist_traits">
                      <T>272336<!--Trait: trait_HighMaintenance--></T>
                    </L>
                  </U>
                </V>
              </L>
            </L>
          </U>
        </L>
      </U>
    </U>
    <U>
      <V n="action" t="unfinished_business_loot">
        <U n="unfinished_business_loot">
          <V n="operation" t="add_objective">
            <U n="add_objective">
              <T n="objective">415640<!--Objective: Objectives_UnfinishedBusiness_Success_Sing--></T>
            </U>
          </V>
          <L n="tests">
            <L>
              <V t="objective_available_test">
                <U n="objective_available_test">
                  <T n="objective">415640<!--Objective: Objectives_UnfinishedBusiness_Success_Sing--></T>
                </U>
              </V>
            </L>
          </L>
        </U>
      </V>
    </U>
    <U>
      <V n="action" t="unfinished_business_loot">
        <U n="unfinished_business_loot">
          <V n="operation" t="add_objective">
            <U n="add_objective">
              <T n="objective">479838<!--Objective: objectives_UnfinishedBusiness_Success_ButterflyCollection--></T>
            </U>
          </V>
          <L n="tests">
            <L>
              <V t="objective_available_test">
                <U n="objective_available_test">
                  <T n="objective">479838<!--Objective: objectives_UnfinishedBusiness_Success_ButterflyCollection--></T>
                </U>
              </V>
            </L>
          </L>
        </U>
      </V>
    </U>
    <U>
      <V n="action" t="unfinished_business_loot">
        <U n="unfinished_business_loot">
          <V n="operation" t="add_objective">
            <U n="add_objective">
              <T n="objective">486085<!--Objective: objectives_UnfinishedBusiness_Success_Archery--></T>
            </U>
          </V>
          <L n="tests">
            <L>
              <V t="objective_available_test">
                <U n="objective_available_test">
                  <T n="objective">486085<!--Objective: objectives_UnfinishedBusiness_Success_Archery--></T>
                </U>
              </V>
            </L>
          </L>
        </U>
      </V>
      <U n="weight">
        <L n="multipliers">
          <U>
            <T n="multiplier">6</T>
            <L n="tests">
              <L>
                <V t="trait">
                  <U n="trait">
                    <L n="whitelist_traits">
                      <T>27914<!--Trait: trait_LovesOutdoors--></T>
                      <T>248831<!--Trait: trait_Lifestyles_Outdoorsy--></T>
                    </L>
                  </U>
                </V>
              </L>
            </L>
          </U>
        </L>
      </U>
    </U>
    <U>
      <V n="action" t="unfinished_business_loot">
        <U n="unfinished_business_loot">
          <V n="operation" t="add_objective">
            <U n="add_objective">
              <T n="objective">486267<!--Objective: objectives_UnfinishedBusiness_Success_Diving--></T>
            </U>
          </V>
          <L n="tests">
            <L>
              <V t="objective_available_test">
                <U n="objective_available_test">
                  <T n="objective">486267<!--Objective: objectives_UnfinishedBusiness_Success_Diving--></T>
                </U>
              </V>
            </L>
          </L>
        </U>
      </V>
    </U>
  </L>
  <L n="tests">
    <L>
      <V t="objective_available_by_type_test">
        <U n="objective_available_by_type_test">
          <E n="category_type">Success</E>
        </U>
      </V>
    </L>
  </L>
</I>