<?xml version="1.0" encoding="utf-8"?>
<I c="RandomWeightedLoot" i="action" m="interactions.utils.loot" n="randomWeightedLoot_AnansisAdvice_Success" s="481762">
  <L n="random_loot_actions">
    <U>
      <V n="action" t="notification_and_dialog">
        <U n="notification_and_dialog">
          <V n="dialog" t="notification">
            <U n="notification">
              <L n="dialog_options">
                <E>DISABLE_CLOSE_BUTTON</E>
              </L>
              <V n="icon" t="enabled">
                <V n="enabled" t="participant">
                  <U n="participant">
                    <L n="participant_type">
                      <E>Object</E>
                    </L>
                  </U>
                </V>
              </V>
              <V n="secondary_icon" t="enabled">
                <V n="enabled" t="participant">
                  <U n="participant">
                    <L n="participant_type">
                      <E>Actor</E>
                    </L>
                  </U>
                </V>
              </V>
              <V n="text" t="single">
                <T n="single">0xDC5EF3C1<!--String: "Many will tell you that a strong Dynasty can't get by without solid alliances. But think about it, do you truly deserve the Kingdom's respect if you can't make it on your own?"--></T>
              </V>
              <V n="title" t="enabled">
                <T n="enabled">0xB119EF5B<!--String: "Anansi shares his sly wisdom..."--></T>
              </V>
            </U>
          </V>
        </U>
      </V>
    </U>
    <U>
      <V n="action" t="notification_and_dialog">
        <U n="notification_and_dialog">
          <V n="dialog" t="notification">
            <U n="notification">
              <L n="dialog_options">
                <E>DISABLE_CLOSE_BUTTON</E>
              </L>
              <V n="icon" t="enabled">
                <V n="enabled" t="participant">
                  <U n="participant">
                    <L n="participant_type">
                      <E>Object</E>
                    </L>
                  </U>
                </V>
              </V>
              <V n="secondary_icon" t="enabled">
                <V n="enabled" t="participant">
                  <U n="participant">
                    <L n="participant_type">
                      <E>Actor</E>
                    </L>
                  </U>
                </V>
              </V>
              <V n="text" t="single">
                <T n="single">0x9530CF31<!--String: "When you're seeking power, having the approval of other Nobles is not always the best path. Being loved by the Commoners can at times be more fruitful...whether you actually care about them or not."--></T>
              </V>
              <V n="title" t="enabled">
                <T n="enabled">0xB119EF5B<!--String: "Anansi shares his sly wisdom..."--></T>
              </V>
            </U>
          </V>
        </U>
      </V>
    </U>
    <U>
      <V n="action" t="notification_and_dialog">
        <U n="notification_and_dialog">
          <V n="dialog" t="notification">
            <U n="notification">
              <L n="dialog_options">
                <E>DISABLE_CLOSE_BUTTON</E>
              </L>
              <V n="icon" t="enabled">
                <V n="enabled" t="participant">
                  <U n="participant">
                    <L n="participant_type">
                      <E>Object</E>
                    </L>
                  </U>
                </V>
              </V>
              <V n="secondary_icon" t="enabled">
                <V n="enabled" t="participant">
                  <U n="participant">
                    <L n="participant_type">
                      <E>Actor</E>
                    </L>
                  </U>
                </V>
              </V>
              <V n="text" t="single">
                <T n="single">0xBD8D2D03<!--String: "The sky is the limit when exploring the Secret Passageways. Who knows where their roads might lead...well, unless you set all the exits yourself."--></T>
              </V>
              <V n="title" t="enabled">
                <T n="enabled">0xB119EF5B<!--String: "Anansi shares his sly wisdom..."--></T>
              </V>
            </U>
          </V>
        </U>
      </V>
    </U>
    <U>
      <V n="action" t="notification_and_dialog">
        <U n="notification_and_dialog">
          <V n="dialog" t="notification">
            <U n="notification">
              <V n="icon" t="enabled">
                <V n="enabled" t="participant">
                  <U n="participant">
                    <L n="participant_type">
                      <E>Object</E>
                    </L>
                  </U>
                </V>
              </V>
              <V n="secondary_icon" t="enabled">
                <V n="enabled" t="participant">
                  <U n="participant">
                    <L n="participant_type">
                      <E>Actor</E>
                    </L>
                  </U>
                </V>
              </V>
              <V n="text" t="single">
                <T n="single">0x87E32183<!--String: "It's foolish to expect you'll have a strong Dynasty if all you do is coddle your family. If you want to achieve greatness, you must lead with subtlety and cunning."--></T>
              </V>
              <V n="title" t="enabled">
                <T n="enabled">0xB119EF5B<!--String: "Anansi shares his sly wisdom..."--></T>
              </V>
            </U>
          </V>
        </U>
      </V>
    </U>
    <U>
      <V n="action" t="notification_and_dialog">
        <U n="notification_and_dialog">
          <V n="dialog" t="notification">
            <U n="notification">
              <L n="dialog_options">
                <E>DISABLE_CLOSE_BUTTON</E>
              </L>
              <V n="icon" t="enabled">
                <V n="enabled" t="participant">
                  <U n="participant">
                    <L n="participant_type">
                      <E>Object</E>
                    </L>
                  </U>
                </V>
              </V>
              <V n="secondary_icon" t="enabled">
                <V n="enabled" t="participant">
                  <U n="participant">
                    <L n="participant_type">
                      <E>Actor</E>
                    </L>
                  </U>
                </V>
              </V>
              <V n="text" t="single">
                <T n="single">0xCCF353B9<!--String: "Hungry for power but don't have much to your name? Who says you have to play by the rules. You could perhaps...Forge a connection to a wealthy family. Even a Noble one."--></T>
              </V>
              <V n="title" t="enabled">
                <T n="enabled">0xB119EF5B<!--String: "Anansi shares his sly wisdom..."--></T>
              </V>
            </U>
          </V>
        </U>
      </V>
    </U>
    <U>
      <V n="action" t="notification_and_dialog">
        <U n="notification_and_dialog">
          <V n="dialog" t="notification">
            <U n="notification">
              <L n="dialog_options">
                <E>DISABLE_CLOSE_BUTTON</E>
              </L>
              <V n="icon" t="enabled">
                <V n="enabled" t="participant">
                  <U n="participant">
                    <L n="participant_type">
                      <E>Object</E>
                    </L>
                  </U>
                </V>
              </V>
              <V n="secondary_icon" t="enabled">
                <V n="enabled" t="participant">
                  <U n="participant">
                    <L n="participant_type">
                      <E>Actor</E>
                    </L>
                  </U>
                </V>
              </V>
              <V n="text" t="single">
                <T n="single">0x47DAD888<!--String: "Secret Babies? Well, you can certainly expand your lineage even if your spouse isn't...fully involved. As long as they <i>believe</i> they're the child's parent, everyone else shall believe the same."--></T>
              </V>
              <V n="title" t="enabled">
                <T n="enabled">0xB119EF5B<!--String: "Anansi shares his sly wisdom..."--></T>
              </V>
            </U>
          </V>
        </U>
      </V>
    </U>
    <U>
      <V n="action" t="notification_and_dialog">
        <U n="notification_and_dialog">
          <V n="dialog" t="notification">
            <U n="notification">
              <L n="dialog_options">
                <E>DISABLE_CLOSE_BUTTON</E>
              </L>
              <V n="icon" t="enabled">
                <V n="enabled" t="participant">
                  <U n="participant">
                    <L n="participant_type">
                      <E>Object</E>
                    </L>
                  </U>
                </V>
              </V>
              <V n="secondary_icon" t="enabled">
                <V n="enabled" t="participant">
                  <U n="participant">
                    <L n="participant_type">
                      <E>Actor</E>
                    </L>
                  </U>
                </V>
              </V>
              <V n="text" t="single">
                <T n="single">0x87E32183<!--String: "It's foolish to expect you'll have a strong Dynasty if all you do is coddle your family. If you want to achieve greatness, you must lead with subtlety and cunning."--></T>
              </V>
              <V n="title" t="enabled">
                <T n="enabled">0xB119EF5B<!--String: "Anansi shares his sly wisdom..."--></T>
              </V>
            </U>
          </V>
        </U>
      </V>
    </U>
    <U>
      <V n="action" t="notification_and_dialog">
        <U n="notification_and_dialog">
          <V n="dialog" t="notification">
            <U n="notification">
              <L n="dialog_options">
                <E>DISABLE_CLOSE_BUTTON</E>
              </L>
              <V n="icon" t="enabled">
                <V n="enabled" t="participant">
                  <U n="participant">
                    <L n="participant_type">
                      <E>Object</E>
                    </L>
                  </U>
                </V>
              </V>
              <V n="secondary_icon" t="enabled">
                <V n="enabled" t="participant">
                  <U n="participant">
                    <L n="participant_type">
                      <E>Actor</E>
                    </L>
                  </U>
                </V>
              </V>
              <V n="text" t="single">
                <T n="single">0x8ACDD526<!--String: "If gaining power feels like a strain, how about you ask someone <i>very</i> high-ranking to dance with you at a Grand Ball? Don't be shy, boldness and confidence can open up so many shortcuts..."--></T>
              </V>
              <V n="title" t="enabled">
                <T n="enabled">0xB119EF5B<!--String: "Anansi shares his sly wisdom..."--></T>
              </V>
            </U>
          </V>
        </U>
      </V>
    </U>
    <U>
      <V n="action" t="notification_and_dialog">
        <U n="notification_and_dialog">
          <V n="dialog" t="notification">
            <U n="notification">
              <L n="dialog_options">
                <E>DISABLE_CLOSE_BUTTON</E>
              </L>
              <V n="icon" t="enabled">
                <V n="enabled" t="participant">
                  <U n="participant">
                    <L n="participant_type">
                      <E>Object</E>
                    </L>
                  </U>
                </V>
              </V>
              <V n="secondary_icon" t="enabled">
                <V n="enabled" t="participant">
                  <U n="participant">
                    <L n="participant_type">
                      <E>Actor</E>
                    </L>
                  </U>
                </V>
              </V>
              <V n="text" t="single">
                <T n="single">0xB375495F<!--String: "A Noble rivalry can be resolved very swiftly if one is <i>cunning</i> with their methods."--></T>
              </V>
              <V n="title" t="enabled">
                <T n="enabled">0xB119EF5B<!--String: "Anansi shares his sly wisdom..."--></T>
              </V>
            </U>
          </V>
        </U>
      </V>
    </U>
    <U>
      <V n="action" t="notification_and_dialog">
        <U n="notification_and_dialog">
          <V n="dialog" t="notification">
            <U n="notification">
              <L n="dialog_options">
                <E>DISABLE_CLOSE_BUTTON</E>
              </L>
              <V n="icon" t="enabled">
                <V n="enabled" t="participant">
                  <U n="participant">
                    <L n="participant_type">
                      <E>Object</E>
                    </L>
                  </U>
                </V>
              </V>
              <V n="secondary_icon" t="enabled">
                <V n="enabled" t="participant">
                  <U n="participant">
                    <L n="participant_type">
                      <E>Actor</E>
                    </L>
                  </U>
                </V>
              </V>
              <V n="text" t="single">
                <T n="single">0xF6E8C6C<!--String: "Your wish to rule a Kingdom is barred by an occupied throne? What makes you think you are fit to rule, if you can't even handle a busy chair? When there's a will...there's a way."--></T>
              </V>
              <V n="title" t="enabled">
                <T n="enabled">0xB119EF5B<!--String: "Anansi shares his sly wisdom..."--></T>
              </V>
            </U>
          </V>
        </U>
      </V>
    </U>
  </L>
</I>